{
    "blue": [
      "#4967DA",
      "#3746DA",
      "#2F17DD",
      "#699ADC"
    ],
    "orange": [
      "#FFA30B",
      "#FF7505",
      "#FF5C04",
      "#FF2E02"
    ],
    "green": [
      "#B5E914",
      "#8FDD09",
      "#21BD00",
      "#109C00"
    ],
    "turquoise": [
      "#08CBD9",
      "#05ADB9",
      "#02869E",
      "#016080"
    ],
    "mint": [
      "#14E2C9",
      "#08D3C1",
      "#07BCAB",
      "#058D80"
    ],
    "purple": [
      "#9468F8",
      "#874DE2",
      "#6748AD",
      "#4A347C"
    ],
    "black": [
      "#000000",
      "#000000",
      "#000000",
      "#000000"
    ],
    "pink": [
      "#FF007F",
      "#EE0F6A",
      "#D50D5F",
      "#84083A"
    ],
    "grey": [
      "#728592",
      "#425765",
      "#263742",
      "#1A2730"
    ],
    "white": [
      "#FFFFFF",
      "#FFFFFF",
      "#FFFFFF",
      "#FFFFFF"
    ]
  }
